<?xml version="1.0" encoding="UTF-8"?>
<!-- edited with XMLSpy v2005 rel. 3 U (http://www.altova.com) by Fred (EDS LTD) -->
<!--
	All Outputs are defined here.
	This allows the build process to create reference data from the actual development.
	See the schema for the meaning of the Elements.
	Change History:
	28/01/2013 - Chris Vincent, added outputs CJR018M (Trac 4765), CJR032A, CJR032B, CJR032C (Trac 4763), 
				 CJR034 and CJR035 (Trac 4762) as part of RFS 3719.
  -->
<Outputs xmlns:xsi="http://www.w3.org/2001/XMLSchema-instance" xsi:noNamespaceSchemaLocation=".\Outputs.xsd">	
	<Output>
		<Id>O_10_13</Id>
		<NReference/>
		<FReference/>
		<Description>Application to set aside a statutory demand</Description>
		<Location>Notice/O_10_13/O_10_13-FO.xml</Location>
		<FinalLocation>Notice/O_10_13/O_10_13-FO.xml</FinalLocation>
	</Output>
	<Output>
		<Id>O_1_3_4</Id>
		<NReference/>
		<FReference/>
		<Description>Order Suspending Warrant/Judgment/(determination)</Description>
		<Location>Notice/O_1_3_4/O_1_3_4-FO.xml</Location>
		<FinalLocation>Notice/O_1_3_4/O_1_3_4-FO.xml</FinalLocation>
	</Output>
	<Output>
		<Id>L_9_1_2_3_4_9_10</Id>
		<NReference/>
		<FReference/>
		<Description>Unable to Serve Letters</Description>
		<Location>Notice/L_9_1_2_3_4_9_10/L_9_1_2_3_4_9_10-FO.xml</Location>
		<FinalLocation>Notice/L_9_1_2_3_4_9_10/L_9_1_2_3_4_9_10-FO.xml</FinalLocation>
	</Output>
	<Output>
		<Id>L_14_1</Id>
		<NReference/>
		<FReference/>
		<Description>Letter to Bailiff bankruptcy/winding up issued </Description>
		<Location>Notice/L_14_1/L_14_1-FO.xml</Location>
		<FinalLocation>Notice/L_14_1/L_14_1-FO.xml</FinalLocation>
	</Output>
	<Output>
		<Id>L_3_9</Id>
		<NReference/>
		<FReference/>
		<Description>Certificate of money provisions </Description>
		<Location>Notice/L_3_9/L_3_9-FO.xml</Location>
		<FinalLocation>Notice/L_3_9/L_3_9-FO.xml</FinalLocation>
	</Output>
	<Output>
		<Id>L_1_2</Id>
		<NReference/>
		<FReference/>
		<Description>Notify process issued/reissued (Letters, 243, General)</Description>
		<Location>Notice/L_1_2/L_1_2-FO.xml</Location>
		<FinalLocation>Notice/L_1_2/L_1_2-FO.xml</FinalLocation>
	</Output>
	<Output>
		<Id>L_1_3</Id>
		<NReference/>
		<FReference/>
		<Description>Request for Part 20 fee (Letters, 244, General)</Description>
		<Location>Notice/L_1_3/L_1_3-FO.xml</Location>
		<FinalLocation>Notice/L_1_3/L_1_3-FO.xml</FinalLocation>
	</Output>
	<Output>
		<Id>L_1_6</Id>
		<NReference/>
		<FReference/>
		<Description>Letter accompanying def/adm/L&amp;T exclusion order (Letters, 247, General) </Description>
		<Location>Notice/L_1_6/L_1_6-FO.xml</Location>
		<FinalLocation>Notice/L_1_6/L_1_6-FO.xml</FinalLocation>
	</Output>
	<Output>
		<Id>L_4_1</Id>
		<NReference/>
		<FReference/>
		<Description>Papers referred to Judge (Letters, 279, General)</Description>
		<Location>Notice/L_4_1/L_4_1-FO.xml</Location>
		<FinalLocation>Notice/L_4_1/L_4_1-FO.xml</FinalLocation>
	</Output>
	<Output>
		<Id>L_4_4</Id>
		<NReference/>
		<FReference/>
		<Description>Request for notes of appeal/judgment (Letters, 282, Orders/Hearing Letters)</Description>
		<Location>Notice/L_4_4/L_4_4-FO.xml</Location>
		<FinalLocation>Notice/L_4_4/L_4_4-FO.xml</FinalLocation>
	</Output>
	<Output>
		<Id>L_5_1</Id>
		<NReference/>
		<FReference/>
		<Description>Case must be transferred prior to enforcement (Letters, 291, General)</Description>
		<Location>Notice/L_5_1/L_5_1-FO.xml</Location>
		<FinalLocation>Notice/L_5_1/L_5_1-FO.xml</FinalLocation>
	</Output>
	<Output>
		<Id>L_6_1_2_3_4_7</Id>
		<NReference/>
		<FReference/>
		<Description>Cash Letters (Letters, 297|298|299|300|303, Cash Section Letters)</Description>
		<Location>Notice/L_6_1_2_3_4_7/L_6_1_2_3_4_7-FO.xml</Location>
		<FinalLocation>Notice/L_6_1_2_3_4_7/L_6_1_2_3_4_7-FO.xml</FinalLocation>
	</Output>
	<Output>
		<Id>L_8_6</Id>
		<NReference/>
		<FReference/>
		<Description>Notice req to DJ for alternative service AE (Letters, 328, Miscellaneous Enforcement)</Description>
		<Location>Notice/L_8_6/L_8_6-FO.xml</Location>
		<FinalLocation>Notice/L_8_6/L_8_6-FO.xml</FinalLocation>
	</Output>
	<Output>
		<Id>L_10_1_2_15_16</Id>
		<NReference/>
		<FReference/>
		<Description>Cost Letters</Description>
		<Location>Notice/L_10_1_2_15_16/L_10_1_2_15_16-FO.xml</Location>
		<FinalLocation>Notice/L_10_1_2_15_16/L_10_1_2_15_16-FO.xml</FinalLocation>
	</Output>
	<Output>
		<Id>L_13_1</Id>
		<NReference/>
		<FReference/>
		<Description>Control warrant - final notice (Letters, 382, Bailiff Section Letters) </Description>
		<Location>Notice/L_13_1/L_13_1-FO.xml</Location>
		<FinalLocation>Notice/L_13_1/L_13_1-FO.xml</FinalLocation>
	</Output>
	<Output>
		<Id>L_13_2</Id>
		<NReference>Ex99</NReference>
		<FReference>Ex99</FReference>
		<Description>Notice of visit by Bailiff (Ex99) (Letters, 383, Bailiff Section Letters) </Description>
		<Location>Notice/L_13_2/L_13_2-FO.xml</Location>
		<FinalLocation>Notice/L_13_2/L_13_2-FO.xml</FinalLocation>
	</Output>
	<Output>
		<Id>L_13_3</Id>
		<NReference>Ex98</NReference>
		<FReference>Ex98</FReference>
		<Description>Not non payment following agreement (Ex98)</Description>
		<Location>Notice/L_13_3/L_13_3-FO.xml</Location>
		<FinalLocation>Notice/L_13_3/L_13_3-FO.xml</FinalLocation>
	</Output>
	<Output>
		<Id>L_13_12</Id>
		<NReference/>
		<FReference/>
		<Description>Application for alternative service (Letters, 393, Bailiff Section Letters) </Description>
		<Location>Notice/L_13_12/L_13_12-FO.xml</Location>
		<FinalLocation>Notice/L_13_12/L_13_12-FO.xml</FinalLocation>
	</Output>
	<Output>
		<Id>L_14_2</Id>
		<NReference/>
		<FReference/>
		<Description>Application for Substituted Service (Bailiff)</Description>
		<Location>Notice/L_14_2/L_14_2-FO.xml</Location>
		<FinalLocation>Notice/L_14_2/L_14_2-FO.xml</FinalLocation>
	</Output>
	<Output>
		<Id>L_14_8</Id>
		<NReference/>
		<FReference/>
		<Description>Letter re app to set aside stat dem (Letters, 402, Insolvency)</Description>
		<Location>Notice/L_14_8/L_14_8-FO.xml</Location>
		<FinalLocation>Notice/L_14_8/L_14_8-FO.xml</FinalLocation>
	</Output>
	<Output>
		<Id>L_4_11</Id>
		<NReference/>
		<FReference/>
		<Description>Letter accompanying copy/amend order</Description>
		<Location>Notice/L_4_11/L_4_11-FO.xml</Location>
		<FinalLocation>Notice/L_4_11/L_4_11-FO.xml</FinalLocation>
	</Output>
	<Output>
		<Id>L_BLANK</Id>
		<NReference/>
		<FReference/>
		<Description>Blank Letter</Description>
		<Location>Notice/L_BLANK/L_BLANK-FO.xml</Location>
		<FinalLocation>Notice/L_BLANK/L_BLANK-FO.xml</FinalLocation>
	</Output>
	<Output>
		<Id>L_BLANK_AE</Id>
		<NReference/>
		<FReference/>
		<Description>Blank AE Letter</Description>
		<Location>Notice/L_BLANK_AE/L_BLANK_AE-FO.xml</Location>
		<FinalLocation>Notice/L_BLANK_AE/L_BLANK_AE-FO.xml</FinalLocation>
	</Output>    
	<Output>
		<Id>L_BLANK_AE_CAPS</Id>
		<NReference/>
		<FReference/>
		<Description>Letter to CAPS</Description>
		<Location>Notice/L_BLANK_AE_CAPS/L_BLANK_AE_CAPS-FO.xml</Location>
		<FinalLocation>Notice/L_BLANK_AE_CAPS/L_BLANK_AE_CAPS-FO.xml</FinalLocation>
	</Output>    	  
	<Output>
		<Id>L_BLANK_CO</Id>
		<NReference/>
		<FReference/>
		<Description>Blank CO Letter</Description>
		<Location>Notice/L_BLANK_CO/L_BLANK_CO-FO.xml</Location>
		<FinalLocation>Notice/L_BLANK_CO/L_BLANK_CO-FO.xml</FinalLocation>
	</Output> 
	<Output>
		<Id>L_BLANK_AX</Id>
		<NReference/>
		<FReference/>
		<Description>Blank AX Letter</Description>
		<Location>Notice/L_BLANK_AX/L_BLANK_AX-FO.xml</Location>
		<FinalLocation>Notice/L_BLANK_AX/L_BLANK_AX-FO.xml</FinalLocation>
	</Output>
	<Output>
		<Id>L_BLANK_AY</Id>
		<NReference/>
		<FReference/>
		<Description>Blank AY Letter</Description>
		<Location>Notice/L_BLANK_AY/L_BLANK_AY-FO.xml</Location>
		<FinalLocation>Notice/L_BLANK_AY/L_BLANK_AY-FO.xml</FinalLocation>
	</Output>
	<Output>
		<Id>L_BLANK_MED</Id>
		<NReference/>
		<FReference/>
		<Description>Blank Mediation Letter</Description>
		<Location>Notice/L_BLANK_MED/L_BLANK_MED-FO.xml</Location>
		<FinalLocation>Notice/L_BLANK_MED/L_BLANK_MED-FO.xml</FinalLocation>
	</Output>
	<Output>
		<Id>O_10_1</Id>
		<NReference/>
		<FReference/>
		<Description>4.13 Notice to official receiver of winding up order</Description>
		<Location>Notice/O_10_1/O_10_1-FO.xml</Location>
		<FinalLocation>Notice/O_10_1/O_10_1-FO.xml</FinalLocation>
	</Output>
	<Output>
		<Id>O_10_3</Id>
		<NReference/>
		<FReference/>
		<Description>5.3 Interim order of court and order extending effect of order </Description>
		<Location>Notice/O_10_3/O_10_3-FO.xml</Location>
		<FinalLocation>Notice/O_10_3/O_10_3-FO.xml</FinalLocation>
	</Output>
	<Output>
		<Id>O_10_2</Id>
		<NReference/>
		<FReference/>
		<Description>5.2 Interim order of court under section 252 </Description>
		<Location>Notice/O_10_2/O_10_2-FO.xml</Location>
		<FinalLocation>Notice/O_10_2/O_10_2-FO.xml</FinalLocation>
	</Output>
	<Output>
		<Id>O_10_5</Id>
		<NReference/>
		<FReference/>
		<Description>6.15 Order for substituted service </Description>
		<Location>Notice/O_10_5/O_10_5-FO.xml</Location>
		<FinalLocation>Notice/O_10_5/O_10_5-FO.xml</FinalLocation>
	</Output>
	<Output>
		<Id>O_10_6</Id>
		<NReference/>
		<FReference/>
		<Description>6.22 Order dismissing/withdrawing petition </Description>
		<Location>Notice/O_10_6/O_10_6-FO.xml</Location>
		<FinalLocation>Notice/O_10_6/O_10_6-FO.xml</FinalLocation>
	</Output>
	<Output>
		<Id>O_10_7</Id>
		<NReference/>
		<FReference/>
		<Description>6.23 Order adjourning hearing of petition</Description>
		<Location>Notice/O_10_7/O_10_7-FO.xml</Location>
		<FinalLocation>Notice/O_10_7/O_10_7-FO.xml</FinalLocation>
	</Output>
	<Output>
		<Id>O_10_8</Id>
		<NReference/>
		<FReference/>
		<Description>6.24a Order for substitution of petitioner on creditor's petition </Description>
		<Location>Notice/O_10_8/O_10_8-FO.xml</Location>
		<FinalLocation>Notice/O_10_8/O_10_8-FO.xml</FinalLocation>
	</Output>
	<Output>
		<Id>O_10_11</Id>
		<NReference/>
		<FReference/>
		<Description>6.29 Order appointing insolvency practitioner </Description>
		<Location>Notice/O_10_11/O_10_11-FO.xml</Location>
		<FinalLocation>Notice/O_10_11/O_10_11-FO.xml</FinalLocation>
	</Output>
	<Output>
		<Id>O_10_12</Id>
		<NReference/>
		<FReference/>
		<Description>6.30 Bankruptcy order on debtor's petition</Description>
		<Location>Notice/O_10_12/O_10_12-FO.xml</Location>
		<FinalLocation>Notice/O_10_12/O_10_12-FO.xml</FinalLocation>
	</Output>
	<Output>
		<Id>O_10_9</Id>
		<NReference/>
		<FReference/>
		<Description>6.24b Change of carriage order</Description>
		<Location>Notice/O_10_9/O_10_9-FO.xml</Location>
		<FinalLocation>Notice/O_10_9/O_10_9-FO.xml</FinalLocation>
	</Output>
	<Output>
		<Id>O_10_10</Id>
		<NReference/>
		<FReference/>
		<Description>6.25 Bankruptcy Order on Creditor's Petition</Description>
		<Location>Notice/O_10_10/O_10_10-FO.xml</Location>
		<FinalLocation>Notice/O_10_10/O_10_10-FO.xml</FinalLocation>
	</Output>	
	<Output>
		<Id>O_10_14</Id>
		<NReference/>
		<FReference/>
		<Description>6.42 Order of court appointing trustee</Description>
		<Location>Notice/O_10_14/O_10_14-FO.xml</Location>
		<FinalLocation>Notice/O_10_14/O_10_14-FO.xml</FinalLocation>
	</Output>
	<Output>
		<Id>O_10_15</Id>
		<NReference/>
		<FReference/>
		<Description>6.71 Order of Annulment Under Section 282 of the Insolvency Act 1986</Description>
		<Location>Notice/O_10_15/O_10_15-FO.xml</Location>
		<FinalLocation>Notice/O_10_15/O_10_15-FO.xml</FinalLocation>
	</Output>
	<Output>
		<Id>O_10_16</Id>
		<NReference/>
		<FReference/>
		<Description>6.77 Certificate of discharge</Description>
		<Location>Notice/O_10_16/O_10_16-FO.xml</Location>
		<FinalLocation>Notice/O_10_16/O_10_16-FO.xml</FinalLocation>
	</Output>
	<Output>
		<Id>O_10_17</Id>
		<NReference/>
		<FReference/>
		<Description>Order on application to set aside a statutory demand</Description>
		<Location>Notice/O_10_17/O_10_17-FO.xml</Location>
		<FinalLocation>Notice/O_10_17/O_10_17-FO.xml</FinalLocation>
	</Output>
	<Output>
		<Id>O_10_18</Id>
		<NReference/>
		<FReference/>
		<Description>General order</Description>
		<Location>Notice/O_10_18/O_10_18-FO.xml</Location>
		<FinalLocation>Notice/O_10_18/O_10_18-FO.xml</FinalLocation>
	</Output>
	<Output>
		<Id>O_10_20</Id>
		<NReference/>
		<FReference/>
		<Description>Request for notification of earlier proceedings</Description>
		<Location>Notice/O_10_20/O_10_20-FO.xml</Location>
		<FinalLocation>Notice/O_10_20/O_10_20-FO.xml</FinalLocation>
	</Output>
	<Output>
		<Id>O_10_19</Id>
		<NReference/>
		<FReference/>
		<Description>Order on application</Description>
		<Location>Notice/O_10_19/O_10_19-FO.xml</Location>
		<FinalLocation>Notice/O_10_19/O_10_19-FO.xml</FinalLocation>
	</Output>
	<Output>
		<Id>O_10_4</Id>
		<NReference/>
		<FReference/>
		<Description>5.3a Order extending effect of interim order</Description>
		<Location>Notice/O_10_4/O_10_4-FO.xml</Location>
		<FinalLocation>Notice/O_10_4/O_10_4-FO.xml</FinalLocation>
	</Output>
	<Output>
		<Id>O_11_1_2_3_4</Id>
		<NReference/>
		<FReference/>
		<Description>Insolvency Order</Description>
		<Location>Notice/O_11_1_2_3_4/O_11_1_2_3_4-FO.xml</Location>
		<FinalLocation>Notice/O_11_1_2_3_4/O_11_1_2_3_4-FO.xml</FinalLocation>
	</Output>
	<Output>
		<Id>CJR002</Id>
		<NReference>N205A</NReference>
		<FReference>N205A</FReference>
		<Description>Notice of issue (specified amount) (&amp; request for judgment)</Description>
		<!-- added &amp; request for judgument upon release 2 uct defect -->
		<Location>Notice/CJR002/CJR002-FO.xml</Location>
		<FinalLocation>Notice/CJR002/CJR002-FO.xml</FinalLocation>
	</Output>
	<Output>
		<Id>CJR003</Id>
		<NReference>N205B</NReference>
		<FReference>N205B</FReference>
		<Description>Notice of issue (unspecified amount) (&amp; request for judgment)</Description>
		<!-- added &amp; request for judgument upon release 2 uct defect -->
		<Location>Notice/CJR003/CJR003-FO.xml</Location>
		<FinalLocation>Notice/CJR003/CJR003-FO.xml</FinalLocation>
	</Output>
	<Output>
		<Id>CJR009</Id>
		<NReference>N215</NReference>
		<FReference>N215</FReference>
		<Description>Certificate of Service</Description>
		<Location>Notice/CJR009/CJR009-FO.xml</Location>
		<FinalLocation>Notice/CJR009/CJR009-FO.xml</FinalLocation>
	</Output>
	<Output>
		<Id>CJR010</Id>
		<NReference>N216</NReference>
		<FReference>N216</FReference>
		<Description>Notice of non-service</Description>
		<Location>Notice/CJR010/CJR010-FO.xml</Location>
		<FinalLocation>Notice/CJR010/CJR010-FO.xml</FinalLocation>
	</Output>
	<Output>
		<Id>CJR011</Id>
		<NReference>N10</NReference>
		<FReference>N10</FReference>
		<Description>Notice that acknowledgement of service has been filed</Description>
		<Location>Notice/CJR011/CJR011-FO.xml</Location>
		<FinalLocation>Notice/CJR011/CJR011-FO.xml</FinalLocation>
	</Output>
	<Output>
		<Id>CJR012</Id>
		<NReference>N236</NReference>
		<FReference>N236</FReference>
		<Description>Notice of Defence that amount claimed has been paid</Description>
		<Location>Notice/CJR012/CJR012-FO.xml</Location>
		<FinalLocation>Notice/CJR012/CJR012-FO.xml</FinalLocation>
	</Output>
	<Output>
		<Id>CJR013</Id>
		<NReference>N225A</NReference>
		<FReference>N225A</FReference>
		<Description>Notice of Part Admission (Specified Amount) </Description>
		<Location>Notice/CJR013/CJR013-FO.xml</Location>
		<FinalLocation>Notice/CJR013/CJR013-FO.xml</FinalLocation>
	</Output>
	<Output>
		<Id>CJR014</Id>
		<NReference>N226</NReference>
		<FReference>N226</FReference>
		<Description>Notice of Admission (unspecified amount)</Description>
		<Location>Notice/CJR014/CJR014-FO.xml</Location>
		<FinalLocation>Notice/CJR014/CJR014-FO.xml</FinalLocation>
	</Output>
	<Output>
		<Id>CJR016</Id>
		<NReference/>
		<FReference/>
		<Description>PROFORMA LETTER IN MULTI DEFENDANT CLAIMS</Description>
		<Location>Notice/CJR016/CJR016-FO.xml</Location>
		<FinalLocation>Notice/CJR016/CJR016-FO.xml</FinalLocation>
	</Output>
	<Output>
		<Id>CJR018A</Id>
		<NReference>N271</NReference>
		<FReference>N271</FReference>
		<Description>Notice of transfer of proceedings</Description>
		<Location>Notice/CJR018A/CJR018A-FO.xml</Location>
		<FinalLocation>Notice/CJR018A/CJR018A-FO.xml</FinalLocation>
	</Output>
	<Output>
		<Id>CJR018B</Id>
		<NReference>N271</NReference>
		<FReference>N271</FReference>
		<Description>Notice of transfer of proceedings</Description>
		<Location>Notice/CJR018B/CJR018B-FO.xml</Location>
		<FinalLocation>Notice/CJR018B/CJR018B-FO.xml</FinalLocation>
	</Output>
	<Output>
		<Id>CJR018C</Id>
		<NReference>N271</NReference>
		<FReference>N271</FReference>
		<Description>Notice of transfer of proceedings</Description>
		<Location>Notice/CJR018C/CJR018C-FO.xml</Location>
		<FinalLocation>Notice/CJR018C/CJR018C-FO.xml</FinalLocation>
	</Output>
	<Output>
		<Id>CJR018D</Id>
		<NReference>N271</NReference>
		<FReference>N271</FReference>
		<Description>Notice of transfer of proceedings</Description>
		<Location>Notice/CJR018D/CJR018D-FO.xml</Location>
		<FinalLocation>Notice/CJR018D/CJR018D-FO.xml</FinalLocation>
	</Output>
	<Output>
		<Id>CJR018E</Id>
		<NReference>N271</NReference>
		<FReference>N271</FReference>
		<Description>Notice of transfer of proceedings</Description>
		<Location>Notice/CJR018E/CJR018E-FO.xml</Location>
		<FinalLocation>Notice/CJR018E/CJR018E-FO.xml</FinalLocation>
	</Output>
	<Output>
		<Id>CJR018F</Id>
		<NReference>N271</NReference>
		<FReference>N271</FReference>
		<Description>Notice of transfer of proceedings</Description>
		<Location>Notice/CJR018F/CJR018F-FO.xml</Location>
		<FinalLocation>Notice/CJR018F/CJR018F-FO.xml</FinalLocation>
	</Output>
	<Output>
		<Id>CJR018G</Id>
		<NReference>N271</NReference>
		<FReference>N271</FReference>
		<Description>Notice of transfer of proceedings</Description>
		<Location>Notice/CJR018G/CJR018G-FO.xml</Location>
		<FinalLocation>Notice/CJR018G/CJR018G-FO.xml</FinalLocation>
	</Output>
	<Output>
		<Id>CJR018H</Id>
		<NReference>N271</NReference>
		<FReference>N271</FReference>
		<Description>Notice of transfer of proceedings</Description>
		<Location>Notice/CJR018H/CJR018H-FO.xml</Location>
		<FinalLocation>Notice/CJR018H/CJR018H-FO.xml</FinalLocation>
	</Output>
	<Output>
		<Id>CJR018I</Id>
		<NReference>N271</NReference>
		<FReference>N271</FReference>
		<Description>Notice of transfer of proceedings</Description>
		<Location>Notice/CJR018I/CJR018I-FO.xml</Location>
		<FinalLocation>Notice/CJR018I/CJR018I-FO.xml</FinalLocation>
	</Output>
	<Output>
		<Id>CJR018J</Id>
		<NReference>N271</NReference>
		<FReference>N271</FReference>
		<Description>Notice of transfer of proceedings</Description>
		<Location>Notice/CJR018J/CJR018J-FO.xml</Location>
		<FinalLocation>Notice/CJR018J/CJR018J-FO.xml</FinalLocation>
	</Output>
	<Output>
		<Id>CJR018K</Id>
		<NReference>N271</NReference>
		<FReference>N271</FReference>
		<Description>Notice of transfer of proceedings</Description>
		<Location>Notice/CJR018K/CJR018K-FO.xml</Location>
		<FinalLocation>Notice/CJR018K/CJR018K-FO.xml</FinalLocation>
	</Output>
	<Output>
		<Id>CJR018L</Id>
		<NReference>N271</NReference>
		<FReference>N271</FReference>
		<Description>Notice of transfer of proceedings</Description>
		<Location>Notice/CJR018L/CJR018L-FO.xml</Location>
		<FinalLocation>Notice/CJR018L/CJR018L-FO.xml</FinalLocation>
	</Output>
	<Output>
		<Id>CJR018M</Id>
		<NReference>N271</NReference>
		<FReference>N271</FReference>
		<Description>Notice of transfer of proceedings</Description>
		<Location>Notice/CJR018M/CJR018M-FO.xml</Location>
		<FinalLocation>Notice/CJR018M/CJR018M-FO.xml</FinalLocation>
	</Output>
	<Output>
		<Id>CJR019</Id>
		<NReference>N153</NReference>
		<FReference>N153</FReference>
		<Description>Notice of Allocation or Listing Hearing</Description>
		<Location>Notice/CJR019/CJR019-FO.xml</Location>
		<FinalLocation>Notice/CJR019/CJR019-FO.xml</FinalLocation>
	</Output>
	<Output>
		<Id>CJR020</Id>
		<NReference>N154</NReference>
		<FReference>N154</FReference>
		<Description>Notice of Allocation to Fast Track</Description>
		<Location>Notice/CJR020/CJR020-FO.xml</Location>
		<FinalLocation>Notice/CJR020/CJR020-FO.xml</FinalLocation>
	</Output>
	<Output>
		<Id>CJR021</Id>
		<NReference>N155</NReference>
		<FReference>N155</FReference>
		<Description>Notice of Allocation to the Multi-track</Description>
		<Location>Notice/CJR021/CJR021-FO.xml</Location>
		<FinalLocation>Notice/CJR021/CJR021-FO.xml</FinalLocation>
	</Output>
	<Output>
		<Id>CJR022</Id>
		<NReference>N156</NReference>
		<FReference>N156</FReference>
		<Description>Request for further information (allocation)</Description>
		<Location>Notice/CJR022/CJR022-FO.xml</Location>
		<FinalLocation>Notice/CJR022/CJR022-FO.xml</FinalLocation>
	</Output>
	<Output>
		<Id>CJR023A</Id>
		<NReference>N157</NReference>
		<FReference>N157</FReference>
		<Description>Notice of Allocation to the Small Claims Track (hearing)</Description>
		<Location>Notice/CJR023A/CJR023A-FO.xml</Location>
		<FinalLocation>Notice/CJR023A/CJR023A-FO.xml</FinalLocation>
	</Output>
	<Output>
		<Id>CJR023B</Id>
		<NReference>N159</NReference>
		<FReference>N159</FReference>
		<Description>Notice of Allocation to the Small Claims Track (no hearing)</Description>
		<Location>Notice/CJR023B/CJR023B-FO.xml</Location>
		<FinalLocation>Notice/CJR023B/CJR023B-FO.xml</FinalLocation>
	</Output>
	<Output>
		<Id>CJR023C</Id>
		<NReference>N160</NReference>
		<FReference>N160</FReference>
		<Description>Notice of Allocation to the Small Claims Track (parties consent)</Description>
		<Location>Notice/CJR023C/CJR023C-FO.xml</Location>
		<FinalLocation>Notice/CJR023C/CJR023C-FO.xml</FinalLocation>
	</Output>
	<Output>
		<Id>CJR023D</Id>
		<NReference>N158</NReference>
		<FReference>N158</FReference>
		<Description>Notice of Allocation to the Small Claims Track (preliminary hearing)</Description>
		<Location>Notice/CJR023D/CJR023D-FO.xml</Location>
		<FinalLocation>Notice/CJR023D/CJR023D-FO.xml</FinalLocation>
	</Output>
	<Output>
		<Id>CJR024</Id>
		<NReference>N24</NReference>
		<FReference>FE37</FReference>
		<Description>Notice of PTR/Adjnd/Restored/Hrg/Management Conference</Description>
		<Location>Notice/CJR024/CJR024-FO.xml</Location>
		<FinalLocation>Notice/CJR024/CJR024-Final-FO.xml</FinalLocation>
	</Output>
	<Output>
		<Id>CJR027</Id>
		<NReference>N244A</NReference>
		<FReference>N244A</FReference>
		<Description>Notice of Hearing of Application</Description>
		<Location>Notice/CJR027/CJR027-FO.xml</Location>
		<FinalLocation>Notice/CJR027/CJR027-FO.xml</FinalLocation>
	</Output>
	<Output>
		<Id>CJR028</Id>
		<NReference>N172</NReference>
		<FReference>N172</FReference>
		<Description>Notice of Trial Date</Description>
		<Location>Notice/CJR028/CJR028-FO.xml</Location>
		<FinalLocation>Notice/CJR028/CJR028-FO.xml</FinalLocation>
	</Output>
	<Output>
		<Id>CJR030</Id>
		<NReference>N20</NReference>
		<FReference>N20</FReference>
		<Description>Witness Summons</Description>
		<Location>Notice/CJR030/CJR030-FO.xml</Location>
		<FinalLocation>Notice/CJR030/CJR030-FO.xml</FinalLocation>
	</Output>
	<Output>
		<Id>CJR031</Id>
		<NReference>N152</NReference>
		<FReference>N152</FReference>
		<Description>Notice that Defence/Counterclaim has been filed</Description>
		<Location>Notice/CJR031/CJR031-FO.xml</Location>
		<FinalLocation>Notice/CJR031/CJR031-FO.xml</FinalLocation>
	</Output>
	<Output>
		<Id>CJR032A</Id>
		<NReference>N149A</NReference>
		<FReference>N149A</FReference>
		<Description>Notice of proposed allocation to the Small Claims Track</Description>
		<Location>Notice/CJR032A/CJR032A-FO.xml</Location>
		<FinalLocation>Notice/CJR032A/CJR032A-FO.xml</FinalLocation>
	</Output>
	<Output>
		<Id>CJR032B</Id>
		<NReference>N149B</NReference>
		<FReference>N149B</FReference>
		<Description>Notice of proposed allocation to the Fast Track</Description>
		<Location>Notice/CJR032B/CJR032B-FO.xml</Location>
		<FinalLocation>Notice/CJR032B/CJR032B-FO.xml</FinalLocation>
	</Output>
	<Output>
		<Id>CJR032C</Id>
		<NReference>N149C</NReference>
		<FReference>N149C</FReference>
		<Description>Notice of proposed allocation to the Multi-Track</Description>
		<Location>Notice/CJR032C/CJR032C-FO.xml</Location>
		<FinalLocation>Notice/CJR032C/CJR032C-FO.xml</FinalLocation>
	</Output>
	<Output>
		<Id>CJR034</Id>
		<NReference>N261</NReference>
		<FReference>N261</FReference>
		<Description>Provisional Assessment Hearing Notice</Description>
		<Location>Notice/CJR034/CJR034-FO.xml</Location>
		<FinalLocation>Notice/CJR034/CJR034-FO.xml</FinalLocation>
	</Output>
	<Output>
		<Id>CJR035</Id>
		<NReference>N253A</NReference>
		<FReference>N253A</FReference>
		<Description>Notice of Provisional Assessment (general form)</Description>
		<Location>Notice/CJR035/CJR035-FO.xml</Location>
		<FinalLocation>Notice/CJR035/CJR035-FO.xml</FinalLocation>
	</Output>
	<Output>
		<Id>CJR036</Id>
		<NReference>N255</NReference>
		<FReference>N255</FReference>
		<Description>Default Costs Certificate</Description>
		<Location>Notice/CJR036/CJR036-FO.xml</Location>
		<FinalLocation>Notice/CJR036/CJR036-FO.xml</FinalLocation>
	</Output>
	<Output>
		<Id>CJR037</Id>
		<NReference>N256</NReference>
		<FReference>N256</FReference>
		<Description>Final Costs Certificate</Description>
		<Location>Notice/CJR037/CJR037-FO.xml</Location>
		<FinalLocation>Notice/CJR037/CJR037-FO.xml</FinalLocation>
	</Output>
	<Output>
		<Id>CJR038</Id>
		<NReference>N257</NReference>
		<FReference>N257</FReference>
		<Description>Interim Cost Certificate</Description>
		<Location>Notice/CJR038/CJR038-FO.xml</Location>
		<FinalLocation>Notice/CJR038/CJR038-FO.xml</FinalLocation>
	</Output>
	<Output>
		<Id>CJR039</Id>
		<NReference>N253</NReference>
		<FReference>N253</FReference>
		<Description>Notice of Amount Allowed on Provisional Assessment (legal aid only) </Description>
		<Location>Notice/CJR039/CJR039-FO.xml</Location>
		<FinalLocation>Notice/CJR039/CJR039-FO.xml</FinalLocation>
	</Output>
	<Output>
		<Id>CJR040</Id>
		<NReference>N30</NReference>
		<FReference>N30</FReference>
		<Description>Judgment for Claimant (in default)</Description>
		<Location>Notice/CJR040/CJR040-FO.xml</Location>
		<FinalLocation>Notice/CJR040/CJR040-FO.xml</FinalLocation>
	</Output>
	<Output>
		<Id>CJR040a</Id>
		<NReference>N30</NReference>
		<FReference></FReference>
		<Description>Judgment for Claimant (in default)</Description>
		<Location>Notice/CJR040a/CJR040a-FO.xml</Location>
		<FinalLocation>Notice/CJR040a/CJR040a-FO.xml</FinalLocation>
	</Output>	
	<Output>
		<Id>CJR041</Id>
		<NReference>N30(1)</NReference>
		<FReference>N30(1)</FReference>
		<Description>Judgment for Claimant (acceptance)</Description>
		<Location>Notice/CJR041/CJR041-FO.xml</Location>
		<FinalLocation>Notice/CJR041/CJR041-FO.xml</FinalLocation>
	</Output>
	<Output>
		<Id>CJR041a</Id>
		<NReference>N30(1)</NReference>
		<FReference>N30(1)</FReference>
		<Description>Judgment for Claimant (acceptance)</Description>
		<Location>Notice/CJR041a/CJR041a-FO.xml</Location>
		<FinalLocation>Notice/CJR041a/CJR041a-FO.xml</FinalLocation>
	</Output>
	<Output>
		<Id>CJR042</Id>
		<NReference>N30(2)</NReference>
		<FReference>N30(2)</FReference>
		<Description>Judgment for Claimant (after determination)</Description>
		<Location>Notice/CJR042/CJR042-FO.xml</Location>
		<FinalLocation>Notice/CJR042/CJR042-Final-FO.xml</FinalLocation>
	</Output>
	<Output>
		<Id>CJR042a</Id>
		<NReference>N30(2)</NReference>
		<FReference>N30(2)</FReference>
		<Description>Judgment for Claimant (after determination)</Description>
		<Location>Notice/CJR042a/CJR042a-FO.xml</Location>
		<FinalLocation>Notice/CJR042a/CJR042a-Final-FO.xml</FinalLocation>
	</Output>
	<Output>
		<Id>CJR043</Id>
		<NReference>N30(3)</NReference>
		<FReference>N30(3)</FReference>
		<Description>Judgment for Claimant (after redetermination)</Description>
		<Location>Notice/CJR043/CJR043-FO.xml</Location>
		<FinalLocation>Notice/CJR043/CJR043-FO.xml</FinalLocation>
	</Output>
	<Output>
		<Id>CJR046</Id>
		<NReference>N17</NReference>
		<FReference>N17</FReference>
		<Description>Judgment for Claimant (amount to be decided by the court)</Description>
		<Location>Notice/CJR046/CJR046-FO.xml</Location>
		<FinalLocation>Notice/CJR046/CJR046-FO.xml</FinalLocation>
	</Output>
	<Output>
		<Id>CJR049</Id>
		<NReference>N34</NReference>
		<FReference>N34</FReference>
		<Description>Judgment For Claimant (after court decided amount)</Description>
		<Location>Notice/CJR049/CJR049-FO.xml</Location>
		<FinalLocation>Notice/CJR049/CJR049-FO.xml</FinalLocation>
	</Output>
	<Output>
		<Id>CJR050</Id>
		<NReference>N26</NReference>
		<FReference>N26</FReference>
		<Description>Order for Possession</Description>
		<Location>Notice/CJR050/CJR050-FO.xml</Location>
		<FinalLocation>Notice/CJR050/CJR050-Final-FO.xml</FinalLocation>
	</Output>
	<Output>
		<Id>CJR051</Id>
		<NReference>N26A</NReference>
		<FReference>N26A</FReference>
		<Description>Order for Possession (accelerated procedure)(assured shorthold tenancy)</Description>
		<Location>Notice/CJR051/CJR051-FO.xml</Location>
		<FinalLocation>Notice/CJR051/CJR051-Final-FO.xml</FinalLocation>
	</Output>
	<Output>
		<Id>CJR052</Id>
		<NReference>N27</NReference>
		<FReference>N27</FReference>
		<Description>Order for Possession on Forfeiture (for rent arrears)</Description>
		<Location>Notice/CJR052/CJR052-FO.xml</Location>
		<FinalLocation>Notice/CJR052/CJR052-FO.xml</FinalLocation>
	</Output>
	<Output>
		<Id>CJR053</Id>
		<NReference>N28</NReference>
		<FReference>N28</FReference>
		<Description>Order for Possession (rented premises)(suspended)</Description>
		<Location>Notice/CJR053/CJR053-FO.xml</Location>
		<FinalLocation>Notice/CJR053/CJR053-FO.xml</FinalLocation>
	</Output>
	<Output>
		<Id>CJR054</Id>
		<NReference>N31</NReference>
		<FReference>N31</FReference>
		<Description>Order for Possession (mortgaged premises)(suspended)</Description>
		<Location>Notice/CJR054/CJR054-FO.xml</Location>
		<FinalLocation>Notice/CJR054/CJR054-FO.xml</FinalLocation>
	</Output>
	<Output>
		<Id>CJR055</Id>
		<NReference>N28A</NReference>
		<FReference>N28A</FReference>
		<Description>Order for possession (rented premises) (postponed)</Description>
		<Location>Notice/CJR055/CJR055-FO.xml</Location>
		<FinalLocation>Notice/CJR055/CJR055-FO.xml</FinalLocation>
	</Output>
	<Output>
		<Id>CJR060</Id>
		<NReference>N24</NReference>
		<FReference>N24</FReference>
		<Description>General Directions Order</Description>
		<Location>Notice/CJR060/CJR060-FO.xml</Location>
		<FinalLocation>Notice/CJR060/CJR060-Final-FO.xml</FinalLocation>
	</Output>
	<Output>
		<Id>CJR061</Id>
		<NReference>N113</NReference>
		<FReference>N113</FReference>
		<Description>Anti-Social Behaviour (order under section 1 of the crime and disorder act 1998)</Description>
		<Location>Notice/CJR061/CJR061-FO.xml</Location>
		<FinalLocation>Notice/CJR061/CJR061-FO.xml</FinalLocation>
	</Output>
	<Output>
		<Id>CJR065</Id>
		<NReference>N24</NReference>
		<FReference>FE37</FReference>
		<Description>General Form of Judgment or Order</Description>
		<Location>Notice/CJR065/CJR065-FO.xml</Location>
		<FinalLocation>Notice/CJR065/CJR065-FO.xml</FinalLocation>
	</Output>
	<!-- Same Reference number as CJR065 -->
	<Output>
		<Id>CJR065A</Id>
		<NReference>N24</NReference>
		<FReference>N24</FReference>
		<Description>General Form of Judgment or Order</Description>
		<Location>Notice/CJR065A/CJR065A-FO.xml</Location>
		<FinalLocation>Notice/CJR065A/CJR065A-Final-FO.xml</FinalLocation>
	</Output>
	<!-- Same Reference number as CJR065 -->
	<Output>
		<Id>CJR065B</Id>
		<NReference>N24</NReference>
		<FReference>N24</FReference>
		<Description>General Form of Judgment or Order</Description>
		<Location>Notice/CJR065B/CJR065B-FO.xml</Location>
		<FinalLocation>Notice/CJR065B/CJR065B-FO.xml</FinalLocation>
	</Output>
	<!-- Same Reference number as CJR065 -->
	<Output>
		<Id>CJR065C</Id>
		<NReference>N24</NReference>
		<FReference>FE37</FReference>
		<Description>General Form of Judgment or Order</Description>
		<Location>Notice/CJR065C/CJR065C-FO.xml</Location>
		<FinalLocation>Notice/CJR065C/CJR065C-Final-FO.xml</FinalLocation>
	</Output>
	<!-- Same Reference number as CJR065 -->
	<Output>
		<Id>CJR065_DO</Id>
		<NReference>N24</NReference>
		<FReference>FE37</FReference>
		<Description>General Form of Judgment or Order</Description>
		<Location>Notice/CJR065_DO/CJR065_DO-FO.xml</Location>
		<FinalLocation>Notice/CJR065_DO/CJR065_DO-FO.xml</FinalLocation>
	</Output>
	<Output>
		<Id>CJR069</Id>
		<NReference>N24</NReference>
		<FReference>N24</FReference>
		<Description>Standard Order for stay for settlement</Description>
		<Location>Notice/CJR069/CJR069-FO.xml</Location>
		<FinalLocation>Notice/CJR069/CJR069-Final-FO.xml</FinalLocation>
	</Output>
	<!-- Same Reference number as CJR065 -->
	<Output>
		<Id>CJR070</Id>
		<NReference>N24</NReference>
		<FReference>N24</FReference>
		<Description>Standard Order for further stay</Description>
		<Location>Notice/CJR070/CJR070-FO.xml</Location>
		<FinalLocation>Notice/CJR070/CJR070-Final-FO.xml</FinalLocation>
	</Output>
	<!-- Same Reference number as CJR065 -->
	<Output>
		<Id>CJR071</Id>
		<NReference>N24</NReference>
		<FReference>N24</FReference>
		<Description>Standard Order - end of stay for settlement and no DQs or notice of settlement filed</Description>
		<Location>Notice/CJR071/CJR071-FO.xml</Location>
		<FinalLocation>Notice/CJR071/CJR071-FO.xml</FinalLocation>
	</Output>
	<Output>
		<Id>CJR072</Id>
		<NReference>N24</NReference>
		<FReference>N24</FReference>
		<Description>Standard Order for Failure to File Listing Questionnaire</Description>
		<Location>Notice/CJR072/CJR072-FO.xml</Location>
		<FinalLocation>Notice/CJR072/CJR072-FO.xml</FinalLocation>
	</Output>
	<Output>
		<Id>CJR073</Id>
		<NReference>N217</NReference>
		<FReference>N217</FReference>
		<Description>Order For Substituted Service</Description>
		<Location>Notice/CJR073/CJR073-FO.xml</Location>
		<FinalLocation>Notice/CJR073/CJR073-FO.xml</FinalLocation>
	</Output>
	<Output>
		<Id>CJR080</Id>
		<NReference>N39</NReference>
		<FReference>N39</FReference>
		<Description>Order to Attend Court for Questioning</Description>
		<Location>Notice/CJR080/CJR080-FO.xml</Location>
		<FinalLocation>Notice/CJR080/CJR080-FO.xml</FinalLocation>
	</Output>
	<Output>
		<Id>CJR081</Id>
		<NReference>N40A</NReference>
		<FReference>N40A</FReference>
		<Description>Warrant of Arrest for Disobedience</Description>
		<Location>Notice/CJR081/CJR081-FO.xml</Location>
		<FinalLocation>Notice/CJR081/CJR081-FO.xml</FinalLocation>
	</Output>
	<Output>
		<Id>CJR082</Id>
		<NReference>N40B</NReference>
		<FReference>N40B</FReference>
		<Description>Warrant of Committal for Disobedience</Description>
		<Location>Notice/CJR082/CJR082-FO.xml</Location>
		<FinalLocation>Notice/CJR082/CJR082-FO.xml</FinalLocation>
	</Output>
	<Output>
		<Id>CJR083</Id>
		<NReference>N79A</NReference>
		<FReference>N79A</FReference>
		<Description>Suspended Committal Order for Disobedience</Description>
		<Location>Notice/CJR083/CJR083-FO.xml</Location>
		<FinalLocation>Notice/CJR083/CJR083-FO.xml</FinalLocation>
	</Output>
	<Output>
		<Id>CJR090</Id>
		<NReference>N37</NReference>
		<FReference>N37</FReference>
		<Description>Hardship Payment Order</Description>
		<Location>Notice/CJR090/CJR090-FO.xml</Location>
		<FinalLocation>Notice/CJR090/CJR090-FO.xml</FinalLocation>
	</Output>
	<Output>
		<Id>CJR091</Id>
		<NReference>N84</NReference>
		<FReference>N84</FReference>
		<Description>Interim Third Party Debt Order</Description>
		<Location>Notice/CJR091/CJR091-FO.xml</Location>
		<FinalLocation>Notice/CJR091/CJR091-FO.xml</FinalLocation>
	</Output>
	<Output>
		<Id>CJR092</Id>
		<NReference>N85</NReference>
		<FReference>N85</FReference>
		<Description>Final Third Party Debt Order</Description>
		<Location>Notice/CJR092/CJR092-FO.xml</Location>
		<FinalLocation>Notice/CJR092/CJR092-FO.xml</FinalLocation>
	</Output>
	<Output>
		<Id>CJR093</Id>
		<NReference>N86</NReference>
		<FReference>FE8</FReference>
		<Description>Interim Charging Order </Description>
		<Location>Notice/CJR093/CJR093-FO.xml</Location>
		<FinalLocation>Notice/CJR093/CJR093-FO.xml</FinalLocation>
	</Output>
	<Output>
		<Id>CJR094</Id>
		<NReference>N87</NReference>
		<FReference>FE9</FReference>
		<Description>Final Charging Order</Description>
		<Location>Notice/CJR094/CJR094-FO.xml</Location>
		<FinalLocation>Notice/CJR094/CJR094-Final-FO.xml</FinalLocation>
	</Output>
	<Output>
		<Id>CJR100</Id>
		<NReference>N142</NReference>
		<FReference>N142</FReference>
		<Description>Guardianship Order (Housing Act 1996, Mental Health Act 1983)</Description>
		<Location>Notice/CJR100/CJR100-FO.xml</Location>
		<FinalLocation>Notice/CJR100/CJR100-FO.xml</FinalLocation>
	</Output>
	<Output>
		<Id>CJR101</Id>
		<NReference>N143</NReference>
		<FReference>N143</FReference>
		<Description>Hospital Order (Housing Act 1996, Mental Health Act 1983)</Description>
		<Location>Notice/CJR101/CJR101-FO.xml</Location>
		<FinalLocation>Notice/CJR101/CJR101-FO.xml</FinalLocation>
	</Output>
	<Output>
		<Id>CJR102</Id>
		<NReference>N146</NReference>
		<FReference>N146</FReference>
		<Description>Warrant of Arrest (housing act 1996)</Description>
		<Location>Notice/CJR102/CJR102-FO.xml</Location>
		<FinalLocation>Notice/CJR102/CJR102-FO.xml</FinalLocation>
	</Output>
	<Output>
		<Id>CJR103</Id>
		<NReference>N147</NReference>
		<FReference>N147</FReference>
		<Description>Remand Order (housing act 1996) (bail granted)</Description>
		<Location>Notice/CJR103/CJR103-FO.xml</Location>
		<FinalLocation>Notice/CJR103/CJR103-FO.xml</FinalLocation>
	</Output>
	<Output>
		<Id>CJR104</Id>
		<NReference>N148</NReference>
		<FReference>N148</FReference>
		<Description>Remand Order (housing act 1996) (bail not granted)</Description>
		<Location>Notice/CJR104/CJR104-FO.xml</Location>
		<FinalLocation>Notice/CJR104/CJR104-FO.xml</FinalLocation>
	</Output>
	<Output>
		<Id>CJR105</Id>
		<NReference>N16/N16(1)</NReference>
		<FReference>N16/N16(1)</FReference>
		<Description>General Form of Injunction for Interlocutory Application or Originating Application</Description>
		<Location>Notice/CJR105/CJR105-FO.xml</Location>
		<FinalLocation>Notice/CJR105/CJR105-FO.xml</FinalLocation>
	</Output>
	<!-- Same Reference number as CJR065 -->
	<Output>
		<Id>CJR170</Id>
		<NReference>N21</NReference>
		<FReference>N21</FReference>
		<Description>Order for Examination of Deponent (before the hearing)</Description>
		<Location>Notice/CJR170/CJR170-FO.xml</Location>
		<FinalLocation>Notice/CJR170/CJR170-FO.xml</FinalLocation>
	</Output>
	<Output>
		<Id>CJR175</Id>
		<NReference>N24</NReference>
		<FReference>N24</FReference>
		<Description>Order for service by alternative method/dispense with service</Description>
		<Location>Notice/CJR175/CJR175-FO.xml</Location>
		<FinalLocation>Notice/CJR175/CJR175-FO.xml</FinalLocation>
	</Output>
	<Output>
		<Id>CJR176</Id>
		<NReference>N171</NReference>
		<FReference>N171</FReference>
		<Description>Notice for date of return of pre-trial checklist</Description>
		<Location>Notice/CJR176/CJR176-FO.xml</Location>
		<FinalLocation>Notice/CJR176/CJR176-FO.xml</FinalLocation>
	</Output>
	<Output>
		<Id>CJR177</Id>
		<NReference>N292</NReference>
		<FReference>N292</FReference>
		<Description>Order on Settlement on Behalf of Child or Patient</Description>
		<Location>Notice/CJR177/CJR177-FO.xml</Location>
		<FinalLocation>Notice/CJR177/CJR177-FO.xml</FinalLocation>
	</Output>
	<Output>
		<Id>CJR178</Id>
		<NReference>N367</NReference>
		<FReference>N367</FReference>
		<Description>Notice of Hearing to Consider Why Fine Should not be Imposed</Description>
		<Location>Notice/CJR178/CJR178-FO.xml</Location>
		<FinalLocation>Notice/CJR178/CJR178-FO.xml</FinalLocation>
	</Output>
	<Output>
		<Id>CJR179</Id>
		<NReference>N205C</NReference>
		<FReference>N205C</FReference>
		<Description>Notice of Issue (non money claim)</Description>
		<Location>Notice/CJR179/CJR179-FO.xml</Location>
		<FinalLocation>Notice/CJR179/CJR179-FO.xml</FinalLocation>
	</Output>
	<Output>
		<Id>CJR183</Id>
		<NReference>N205D</NReference>
		<FReference>N205D</FReference>
		<Description>Notice of Issue (probate claim)</Description>
		<Location>Notice/CJR183/CJR183-FO.xml</Location>
		<FinalLocation>Notice/CJR183/CJR183-FO.xml</FinalLocation>
	</Output>
	<Output>
		<Id>CJR184</Id>
		<NReference>N173</NReference>
		<FReference>N173</FReference>
		<Description>Notice to Pay Fee</Description>
		<Location>Notice/CJR184/CJR184-FO.xml</Location>
		<FinalLocation>Notice/CJR184/CJR184-FO.xml</FinalLocation>
	</Output>
	<Output>
		<Id>CJR185</Id>
		<NReference>N209</NReference>
		<FReference>N209</FReference>
		<Description>Part 8 Notice of Issue</Description>
		<Location>Notice/CJR185/CJR185-FO.xml</Location>
		<FinalLocation>Notice/CJR185/CJR185-FO.xml</FinalLocation>
	</Output>
	<Output>
		<Id>CJR186</Id>
		<NReference>N212</NReference>
		<FReference>N212</FReference>
		<Description>Part 20 Notice of Issue</Description>
		<Location>Notice/CJR186/CJR186-FO.xml</Location>
		<FinalLocation>Notice/CJR186/CJR186-FO.xml</FinalLocation>
	</Output>
	<Output>
		<Id>CJR186A</Id>
		<NReference>N212</NReference>
		<FReference>N212</FReference>
		<Description>Part 20 Notice of Issue</Description>
		<Location>Notice/CJR186A/CJR186A-FO.xml</Location>
		<FinalLocation>Notice/CJR186A/CJR186A-FO.xml</FinalLocation>
	</Output>
	<Output>
		<Id>CJR187</Id>
		<NReference>N206</NReference>
		<FReference>N206</FReference>
		<Description>Notice of Issue (fixed date summons/originating application)</Description>
		<Location>Notice/CJR187/CJR187-FO.xml</Location>
		<FinalLocation>Notice/CJR187/CJR187-FO.xml</FinalLocation>
	</Output>
	<Output>
		<Id>CJR188</Id>
		<NReference>N206A</NReference>
		<FReference>N206A</FReference>
		<Description>Notice of Issue (accelerated possession claim)(assured shorthold tenancy)</Description>
		<Location>Notice/CJR188/CJR188-FO.xml</Location>
		<FinalLocation>Notice/CJR188/CJR188-FO.xml</FinalLocation>
	</Output>
	<Output>
		<Id>CJR189</Id>
		<NReference>N206B</NReference>
		<FReference>N206B</FReference>
		<Description>Notice of Issue (possession claim)</Description>
		<Location>Notice/CJR189/CJR189-FO.xml</Location>
		<FinalLocation>Notice/CJR189/CJR189-FO.xml</FinalLocation>
	</Output>
	<Output>
		<Id>CJR190</Id>
		<NReference>N206D</NReference>
		<FReference>N206D</FReference>
		<Description>Notice of Issue (demotion claim)</Description>
		<Location>Notice/CJR190/CJR190-FO.xml</Location>
		<FinalLocation>Notice/CJR190/CJR190-FO.xml</FinalLocation>
	</Output>
	<Output>
		<Id>CJR199</Id>
		<NReference/>
		<FReference/>
		<Description>Notice of Trial Directions</Description>
		<Location>Notice/CJR199/CJR199-FO.xml</Location>
		<FinalLocation>Notice/CJR199/CJR199-FO.xml</FinalLocation>
	</Output>
	<Output>
		<Id>CJR201</Id>
		<NReference>N243B</NReference>
		<FReference>N243B</FReference>
		<Description>Notice of Instruction to Court Funds Office</Description>
		<Location>Notice/CJR201/CJR201-FO.xml</Location>
		<FinalLocation>Notice/CJR201/CJR201-FO.xml</FinalLocation>
	</Output>
	<Output>
		<Id>CJR202</Id>
		<NReference>N243B</NReference>
		<FReference>N243B</FReference>
		<Description>Notice of Instruction to Court Funds Office</Description>
		<Location>Notice/CJR202/CJR202-FO.xml</Location>
		<FinalLocation>Notice/CJR202/CJR202-FO.xml</FinalLocation>
	</Output>
	<Output>
		<Id>CJR351</Id>
		<NReference>N32(3)</NReference>
		<FReference>N32(3)</FReference>
		<Description>Judgment for Delivery of Goods</Description>
		<Location>Notice/CJR351/CJR351-FO.xml</Location>
		<FinalLocation>Notice/CJR351/CJR351-FO.xml</FinalLocation>
	</Output>
	<Output>
		<Id>CJR352</Id>
		<NReference>N32(4)</NReference>
		<FReference>N32(4)</FReference>
		<Description>Variation Order (Return of Goods)</Description>
		<Location>Notice/CJR352/CJR352-FO.xml</Location>
		<FinalLocation>Notice/CJR352/CJR352-FO.xml</FinalLocation>
	</Output>
	<Output>
		<Id>O_9_1</Id>
		<NReference>N243B</NReference>
		<FReference>N243B</FReference>
		<Description>Notice of Instruction to Court Funds Office</Description>
		<Location>Notice/O_9_1/O_9_1-FO.xml</Location>
		<FinalLocation>Notice/O_9_1/O_9_1-FO.xml</FinalLocation>
	</Output>
	<Output>
		<Id>O_9_2</Id>
		<NReference/>
		<FReference/>
		<Description>Court Funds Office - Form 211</Description>
		<Location>Notice/O_9_2/O_9_2-FO.xml</Location>
		<FinalLocation>Notice/O_9_2/O_9_2-FO.xml</FinalLocation>
	</Output>
	<Output>
		<Id>O_2_6</Id>
		<NReference>N110a</NReference>
		<FReference>N110a</FReference>
		<Description>Power of arrest attached to injunction</Description>
		<Location>Notice/O_2_6/O_2_6-FO.xml</Location>
		<FinalLocation>Notice/O_2_6/O_2_6-FO.xml</FinalLocation>
	</Output>
	<Output>
		<Id>O_5_5</Id>
		<NReference>N289</NReference>
		<FReference>N289</FReference>
		<Description>Judgment for defendant</Description>
		<Location>Notice/O_5_5/O_5_5-FO.xml</Location>
		<FinalLocation>Notice/O_5_5/O_5_5-FO.xml</FinalLocation>
	</Output>
	<Output>
		<Id>O_5_6</Id>
		<NReference>N322</NReference>
		<FReference>N322</FReference>
		<Description>Order for recovery of award</Description>
		<Location>Notice/O_5_6/O_5_6-FO.xml</Location>
		<FinalLocation>Notice/O_5_6/O_5_6-Final-FO.xml</FinalLocation>
	</Output>
	<Output>
		<Id>CJR1424</Id>
		<NReference>N228</NReference>
		<FReference>N228</FReference>
		<Description>Notice of Admission - Return of Goods</Description>
		<Location>Notice/CJR1424/CJR1424-FO.xml</Location>
		<FinalLocation>Notice/CJR1424/CJR1424-FO.xml</FinalLocation>
	</Output>
	<Output>
		<Id>O_7_12_5</Id>
		<NReference/>
		<FReference/>
		<Description>Claimant's reply to defendant's application to vary instalment order</Description>
		<Location>Notice/O_7_12_5/O_7_12_5-FO.xml</Location>
		<FinalLocation>Notice/O_7_12_5/O_7_12_5-FO.xml</FinalLocation>
	</Output>
	<Output>
		<Id>O_7_12_6</Id>
		<NReference/>
		<FReference/>
		<Description>Certificate of judgment or order (for evidence only)</Description>
		<Location>Notice/O_7_12_6/O_7_12_6-FO.xml</Location>
		<FinalLocation>Notice/O_7_12_6/O_7_12_6-FO.xml</FinalLocation>
	</Output>
	<Output>
		<Id>O_3_1_2_5_1</Id>
		<NReference/>
		<FReference/>
		<Description>Order Setting Aside Judgment</Description>
		<Location>Notice/O_3_1_2_5_1/O_3_1_2_5_1-FO.xml</Location>
		<FinalLocation>Notice/O_3_1_2_5_1/O_3_1_2_5_1-FO.xml</FinalLocation>
	</Output>
	<Output>
		<Id>N35</Id>
		<NReference>N35</NReference>
		<FReference>N35</FReference>
		<Description>Variation order</Description>
		<Location>Notice/N35/N35-FO.xml</Location>
		<FinalLocation>Notice/N35/N35-FO.xml</FinalLocation>
	</Output>
	<Output>
		<Id>N35A</Id>
		<NReference>N35A</NReference>
		<FReference>N35A</FReference>
		<Description>Variation order (determination)</Description>
		<Location>Notice/N35A/N35A-FO.xml</Location>
		<FinalLocation>Notice/N35A/N35A-FO.xml</FinalLocation>
	</Output>
	<Output>
		<Id>O_7_8</Id>
		<NReference/>
		<FReference/>
		<Description>Judgment for delivery of goods under paragraph (a) of section 35(4) of the Hire-Purchase Act 1965 or under section 12(4) of the Hire-Purchase Act 1938 or under section 133(1)(i) of the Consumer Credit Act 1974</Description>
		<Location>Notice/O_7_8/O_7_8-FO.xml</Location>
		<FinalLocation>Notice/O_7_8/O_7_8-FO.xml</FinalLocation>
	</Output>
	<Output>
		<Id>N32_2</Id>
		<NReference>N32(2)</NReference>
		<FReference>N32(2)</FReference>
		<Description>Judgment for Delivery of Goods (suspended)</Description>
		<Location>Notice/N32_2/N32_2-FO.xml</Location>
		<FinalLocation>Notice/N32_2/N32_2-FO.xml</FinalLocation>
	</Output>
	<Output>
		<Id>N32_5</Id>
		<NReference>N32_5</NReference>
		<FReference>>N32_5</FReference>
		<Description>Order for Balance of Purchase Price (return of goods)</Description>
		<Location>Notice/N32_5/N32_5-FO.xml</Location>
		<FinalLocation>Notice/N32_5/N32_5-FO.xml</FinalLocation>
	</Output>
	<Output>
		<Id>N32</Id>
		<NReference>N32</NReference>
		<FReference>N32</FReference>
		<Description>Judgment for Delivery of Goods</Description>
		<Location>Notice/N32/N32-FO.xml</Location>
		<FinalLocation>Notice/N32/N32-FO.xml</FinalLocation>
	</Output>	
	<Output>
		<Id>N33</Id>
		<NReference>N33</NReference>
		<FReference>N33</FReference>
		<Description>Judgment for Delivery of Goods Let under regulated consumer hire agreement</Description>
		<Location>Notice/N33/N33-FO.xml</Location>
		<FinalLocation>Notice/N33/N33-FO.xml</FinalLocation>
	</Output>
	<Output>
		<Id>N54</Id>
		<NReference>N54</NReference>
		<FReference>N54</FReference>
		<Description>Notice of Eviction</Description>
		<Location>Notice/N54/N54-FO.xml</Location>
		<FinalLocation>Notice/N54/N54-FO.xml</FinalLocation>
	</Output>
	<Output>
		<Id>N246A</Id>
		<NReference></NReference>
		<FReference></FReference>
		<Description>Reply to application to suspend warrant of control (Order 13, rule 1(2), Order 25, rule 8)</Description>
		<Location>Notice/N246A/N246A-FO.xml</Location>
		<FinalLocation>Notice/N246A/N246A-FO.xml</FinalLocation>
	</Output>
	
	<Output>
		<Id>EX96</Id>
		<NReference/>
		<FReference/>
		<Description>Notice of Appointment (with Bailiff)</Description>
		<Location>Notice/EX96/EX96-FO.xml</Location>
		<FinalLocation>Notice/EX96/EX96-FO.xml</FinalLocation>
	</Output>	
	<Output>
		<Id>N441A</Id>
		<NReference>N441A</NReference>
		<FReference>N441A</FReference>
		<Description>Certificate of Satisfaction or Cancellation of Judgment Debt</Description>
		<Location>Notice/N441A/N441A-FO.xml</Location>
		<FinalLocation>Notice/N441A/N441A-FO.xml</FinalLocation>
	</Output>
	<Output>
		<Id>CO02</Id>
		<NReference>N24</NReference>
		<FReference>N24</FReference>
		<Description>Notice of Hearing</Description>
		<Location>Notice/CO02/CO02-FO.xml</Location>
		<FinalLocation>Notice/CO02/CO02-FO.xml</FinalLocation>
	</Output>
	<Output>
		<Id>CO03</Id>
		<NReference>N24</NReference>
		<FReference>N24</FReference>
		<Description>General Form of Order</Description>
		<Location>Notice/CO03/CO03-FO.xml</Location>
		<FinalLocation>Notice/CO03/CO03-FO.xml</FinalLocation>
	</Output>
	<Output>
		<Id>CO05</Id>
		<NReference>N59</NReference>
		<FReference>N59</FReference>
		<Description>Warrant of Committal to Prison (Section 23 Attachment of Earnings Act 1971)</Description>
		<Location>Notice/CO05/CO05-FO.xml</Location>
		<FinalLocation>Notice/CO05/CO05-FO.xml</FinalLocation>
	</Output>
	<Output>
		<Id>CO09</Id>
		<NReference>N62D</NReference>
		<FReference>N62D</FReference>
		<Description>Summons for Offence Under Attachment of Earnings Act 1971</Description>
		<Location>Notice/CO09/CO09-FO.xml</Location>
		<FinalLocation>Notice/CO09/CO09-FO.xml</FinalLocation>
	</Output>
	<Output>
		<Id>CO10</Id>
		<NReference>N62E</NReference>
		<FReference>N62E</FReference>
		<Description>Summons for Offence Under Attachment of Earnings Act 1971</Description>
		<Location>Notice/CO10/CO10-FO.xml</Location>
		<FinalLocation>Notice/CO10/CO10-FO.xml</FinalLocation>
	</Output>
	<Output>
		<Id>CO13</Id>
		<NReference>N66</NReference>
		<FReference>N66</FReference>
		<Description>Consolidated Attachment of Earnings Order</Description>
		<Location>Notice/CO13/CO13-FO.xml</Location>
		<FinalLocation>Notice/CO13/CO13-FO.xml</FinalLocation>
	</Output>
	<Output>
		<Id>CO14</Id>
		<NReference>N66A</NReference>
		<FReference>N66A</FReference>
		<Description>Notice of Application for Consolidated Attachment of Earnings Order</Description>
		<Location>Notice/CO14/CO14-FO.xml</Location>
		<FinalLocation>Notice/CO14/CO14-FO.xml</FinalLocation>
	</Output>
	<Output>
		<Id>CO15</Id>
		<NReference>N66(B)</NReference>
		<FReference>N66(B)</FReference>
		<Description>Order adding debt to Consolidated Attachment of Earnings Order at a hearing</Description>
		<Location>Notice/CO15/CO15-FO.xml</Location>
		<FinalLocation>Notice/CO15/CO15-FO.xml</FinalLocation>
	</Output>
	<Output>
		<Id>CO16</Id>
		<NReference>N66(C)</NReference>
		<FReference>N66(C)</FReference>
		<Description>Order adding debt to a Consolidated Attachment of Earnings Order by substitution of a new order [at a hearing]</Description>
		<Location>Notice/CO16/CO16-FO.xml</Location>
		<FinalLocation>Notice/CO16/CO16-FO.xml</FinalLocation>
	</Output>
	<Output>
		<Id>CO17</Id>
		<NReference>N66(D)</NReference>
		<FReference>N66(D)</FReference>
		<Description>Order removing debt from Consolidated Attachment of Earnings Order at a hearing</Description>
		<Location>Notice/CO17/CO17-FO.xml</Location>
		<FinalLocation>Notice/CO17/CO17-FO.xml</FinalLocation>
	</Output>
	<Output>
		<Id>CO18</Id>
		<NReference>N66(E)</NReference>
		<FReference>N66(E)</FReference>
		<Description>Order varying Consolidated Attachment of Earnings Order at a hearing</Description>
		<Location>Notice/CO18/CO18-FO.xml</Location>
		<FinalLocation>Notice/CO18/CO18-FO.xml</FinalLocation>
	</Output>
	<Output>
		<Id>CO19</Id>
		<NReference>N66(F)</NReference>
		<FReference>N66(F)</FReference>
		<Description>Order varying or suspending Consolidated Attachment of Earnings Order at a hearing</Description>
		<Location>Notice/CO19/CO19-FO.xml</Location>
		<FinalLocation>Notice/CO19/CO19-FO.xml</FinalLocation>
	</Output>
	<Output>
		<Id>CO20</Id>
		<NReference>N66(G)</NReference>
		<FReference>N66(G)</FReference>
		<Description>Order discharging Consolidated Attachment of Earnings Order at a hearing</Description>
		<Location>Notice/CO20/CO20-FO.xml</Location>
		<FinalLocation>Notice/CO20/CO20-FO.xml</FinalLocation>
	</Output>
	<Output>
		<Id>CO21</Id>
		<NReference>N66(H)</NReference>
		<FReference>N66(H)</FReference>
		<Description>Notice of Hearing of application for Consolidated Attachment of Earnings Order</Description>
		<Location>Notice/CO21/CO21-FO.xml</Location>
		<FinalLocation>Notice/CO21/CO21-FO.xml</FinalLocation>
	</Output>
	<Output>
		<Id>CO22</Id>
		<NReference>N66(I)</NReference>
		<FReference>N66(I)</FReference>
		<Description>Notice of Application to add case to Consolidated Attachment of Earnings Order at a hearing</Description>
		<Location>Notice/CO22/CO22-FO.xml</Location>
		<FinalLocation>Notice/CO22/CO22-FO.xml</FinalLocation>
	</Output>
	<Output>
		<Id>CO23</Id>
		<NReference>N66(J)</NReference>
		<FReference>N66(J)</FReference>
		<Description>Order [Striking Out] [Dismissing] [Adjourning] application for Consolidated Attachment of Earnings Order at a hearing</Description>
		<Location>Notice/CO23/CO23-FO.xml</Location>
		<FinalLocation>Notice/CO23/CO23-FO.xml</FinalLocation>
	</Output>
	<Output>
		<Id>CO24</Id>
		<NReference>N91</NReference>
		<FReference>N91</FReference>
		<Description>Order of Commitment and/or Imposing a Fine for Assaulting an Officer of the Court or Rescuing Goods</Description>
		<Location>Notice/CO24/CO24-FO.xml</Location>
		<FinalLocation>Notice/CO24/CO24-FO.xml</FinalLocation>
	</Output>
	<Output>
		<Id>CO25</Id>
		<NReference>N94</NReference>
		<FReference>N94</FReference>
		<Description>Administration Order</Description>
		<Location>Notice/CO25/CO25-FO.xml</Location>
		<FinalLocation>Notice/CO25/CO25-FO.xml</FinalLocation>
	</Output>
	<Output>
		<Id>CO26</Id>
		<NReference>N95</NReference>
		<FReference>N95</FReference>
		<Description>Order Revoking/Discharging an Administration Order</Description>
		<Location>Notice/CO26/CO26-FO.xml</Location>
		<FinalLocation>Notice/CO26/CO26-FO.xml</FinalLocation>
	</Output>
	<Output>
		<Id>CO27</Id>
		<NReference>N95A</NReference>
		<FReference>N95A</FReference>
		<Description>Order Suspending or Varying an Administration Order</Description>
		<Location>Notice/CO27/CO27-FO.xml</Location>
		<FinalLocation>Notice/CO27/CO27-FO.xml</FinalLocation>
	</Output>
	<Output>
		<Id>CO28</Id>
		<NReference>N95(A)</NReference>
		<FReference>N95(A)</FReference>
		<Description>Order deleting Debt from Administration Order</Description>
		<Location>Notice/CO28/CO28-FO.xml</Location>
		<FinalLocation>Notice/CO28/CO28-FO.xml</FinalLocation>
	</Output>
	<Output>
		<Id>CO29</Id>
		<NReference>N95(B)</NReference>
		<FReference>N95(B)</FReference>
		<Description>Order adding new debt to Schedule 1 to Administration Order</Description>
		<Location>Notice/CO29/CO29-FO.xml</Location>
		<FinalLocation>Notice/CO29/CO29-FO.xml</FinalLocation>
	</Output>
	<Output>
		<Id>CO30</Id>
		<NReference>N95(D)</NReference>
		<FReference>N95(D)</FReference>
		<Description>District Judge's Order Adding New Debt to Schedule 2 to Administration Order</Description>
		<Location>Notice/CO30/CO30-FO.xml</Location>
		<FinalLocation>Notice/CO30/CO30-FO.xml</FinalLocation>
	</Output>
	<Output>
		<Id>CO31</Id>
		<NReference>N95(E)</NReference>
		<FReference>N95(E)</FReference>
		<Description>Order dismissing Application to Add New Debt to Administration Order</Description>
		<Location>Notice/CO31/CO31-FO.xml</Location>
		<FinalLocation>Notice/CO31/CO31-FO.xml</FinalLocation>
	</Output>
	<Output>
		<Id>CO32</Id>
		<NReference>N95(F)</NReference>
		<FReference>N95(F)</FReference>
		<Description>Order setting aside Administration Order</Description>
		<Location>Notice/CO32/CO32-FO.xml</Location>
		<FinalLocation>Notice/CO32/CO32-FO.xml</FinalLocation>
	</Output>
	<Output>
		<Id>CO33</Id>
		<NReference>N95(G)</NReference>
		<FReference>N95(G)</FReference>
		<Description>Order to disregard late objection to Administration Order</Description>
		<Location>Notice/CO33/CO33-FO.xml</Location>
		<FinalLocation>Notice/CO33/CO33-FO.xml</FinalLocation>
	</Output>
	<Output>
		<Id>CO34</Id>
		<NReference>N95(H)</NReference>
		<FReference>N95(H)</FReference>
		<Description>Order striking out/dismissing/adjourning application for Administration Order</Description>
		<Location>Notice/CO34/CO34-FO.xml</Location>
		<FinalLocation>Notice/CO34/CO34-FO.xml</FinalLocation>
	</Output>
	<Output>
		<Id>CO35</Id>
		<NReference>N95(I)</NReference>
		<FReference>N95(I)</FReference>
		<Description>Order for Hearing of Late Objection to Administration Order</Description>
		<Location>Notice/CO35/CO35-FO.xml</Location>
		<FinalLocation>Notice/CO35/CO35-FO.xml</FinalLocation>
	</Output>
	<Output>
		<Id>CO36</Id>
		<NReference>N112A</NReference>
		<FReference>N112A</FReference>
		<Description>Power of arrest under section 23 (Attachment of Earnings Act 1971):</Description>
		<Location>Notice/CO36/CO36-FO.xml</Location>
		<FinalLocation>Notice/CO36/CO36-FO.xml</FinalLocation>
	</Output>
	<Output>
		<Id>CO37</Id>
		<NReference>N118</NReference>
		<FReference>N118</FReference>
		<Description>Notice to defendant where committal order made, but directed to be suspended under Attachment of Earnings Act 1971</Description>
		<Location>Notice/CO37/CO37-FO.xml</Location>
		<FinalLocation>Notice/CO37/CO37-FO.xml</FinalLocation>
	</Output>
	<Output>
		<Id>CO41</Id>
		<NReference>N370</NReference>
		<FReference>N370</FReference>
		<Description>Order of Commitment or Imposing a Fine for Insult or Misbehaviour</Description>
		<Location>Notice/CO41/CO41-FO.xml</Location>
		<FinalLocation>Notice/CO41/CO41-FO.xml</FinalLocation>
	</Output>
	<Output>
		<Id>CO43</Id>
		<NReference>N374</NReference>
		<FReference>N374</FReference>
		<Description>Notice of Intention to Review</Description>
		<Location>Notice/CO43/CO43-FO.xml</Location>
		<FinalLocation>Notice/CO43/CO43-FO.xml</FinalLocation>
	</Output>
	<Output>
		<Id>CO44</Id>
		<NReference>N374A</NReference>
		<FReference>N374A</FReference>
		<Description>Notice of Intention to Revoke an Administration Order</Description>
		<Location>Notice/CO44/CO44-FO.xml</Location>
		<FinalLocation>Notice/CO44/CO44-FO.xml</FinalLocation>
	</Output>
	<Output>
		<Id>CO52</Id>
		<NReference>N66(K)</NReference>
		<FReference>N66(K)</FReference>
		<Description>Suspended Consolidated Attachment of Earnings Order - Payment by Debtor</Description>
		<Location>Notice/CO52/CO52-FO.xml</Location>
		<FinalLocation>Notice/CO52/CO52-FO.xml</FinalLocation>
	</Output>
	<Output>
		<Id>COLET</Id>
		<NReference/>
		<FReference/>
		<Description>CO Letter to all Parties</Description>
		<Location>Notice/COLET/COLET-FO.xml</Location>
		<FinalLocation>Notice/COLET/COLET-FO.xml</FinalLocation>
	</Output>
	<Output>
		<Id>O_8_12</Id>
		<NReference/>
		<FReference/>
		<Description>nk order - Technology and Construction Court</Description>
		<Location>Notice/O_8_12/O_8_12-FO.xml</Location>
		<FinalLocation>Notice/O_8_12/O_8_12-FO.xml</FinalLocation>
	</Output>
	<Output>
		<Id>O_8_5</Id>
		<NReference/>
		<FReference/>
		<Description>Notice of transfer to Technology and Construction Court</Description>
		<Location>Notice/O_8_5/O_8_5-FO.xml</Location>
		<FinalLocation>Notice/O_8_5/O_8_5-FO.xml</FinalLocation>
	</Output>
	<Output>
		<Id>FE45</Id>
		<NReference/>
		<FReference>FE45</FReference>
		<Description>Order to Attend Court for Questioning</Description>
		<Location>Notice/FE45/FE45-FO.xml</Location>
		<FinalLocation>Notice/FE45/FE45-Final-FO.xml</FinalLocation>
	</Output>
	<Output>
		<Id>X01</Id>
		<NReference/>
		<FReference/>
		<Description>No output QA for warrant creation via event</Description>
		<Location/>
		<FinalLocation/>
		<AltProcess>QAOnly</AltProcess>
	</Output>
</Outputs>