<?xml version="1.0" encoding="UTF-8"?>
<!-- Change History -->
<!-- 10th Jan 2007 - TEMP_caseman defect 374 - MGG, added hint text -->
<!--Question xmlns="http://eds.com/questionxhtml" xmlns:html="http://www.w3.org/TR/REC-html40" xmlns:xsi="http://www.w3.org/2001/XMLSchema-instance" xsi:schemaLocation="http://eds.com/questionxhtml ..\Question.xsd"-->
<Question xmlns:html="http://www.w3.org/TR/REC-html40" xmlns:xsi="http://www.w3.org/2001/XMLSchema-instance" xsi:schemaLocation="http://eds.com/questionxhtml ..\Question.xsd">
	<Id>Q_HearingVenueAddressLine1</Id>
	<Label>Hearing Venue Address Line 2</Label>
	<ObjectName>HearingVenueAddressLine2</ObjectName>
	<Html>
		<input id="HearingVenueAddressLine2" type="text" size="70"></input>
	</Html>
	<Javascript>
		<XPath>/ds/var/page/OracleReportForm/HearingVenueAddressLine2</XPath>
		<ReportVariableName>HEAR_ADDR2</ReportVariableName>
		<ReportVariableValue>Services.getValue(HearingVenueAddressLine2.dataBinding)</ReportVariableValue>
		<ReportVariableCode>906</ReportVariableCode>
		<ParameterType>S</ParameterType>	
		<HintText>Second Line of the Hearing venue address</HintText>
		<isMandatory>return false;</isMandatory>
		<isReadOnly>
			return true;
		</isReadOnly>
		<initialise></initialise>
		<transformToDisplay>
			return (null != value) ? value.toUpperCase() : null;
		</transformToDisplay>
		<transformToModel>
			return (null != value) ? value.toUpperCase() : null;
		</transformToModel>		
		<setDefault>
		</setDefault>		
		<validateOn>
		</validateOn>
		<validate>
		</validate>
		<miscCode>
		</miscCode>
	</Javascript>
</Question>