<?xml version="1.0" encoding="UTF-8"?>
<Question xmlns:html="http://www.w3.org/TR/REC-html40" xmlns:xsi="http://www.w3.org/2001/XMLSchema-instance" xsi:schemaLocation="http://eds.com/questionxhtml ..\Question.xsd">
	<Id>481</Id>
	<Label>Single payment amount</Label>
	<ObjectName>SinglePaymentAmnt</ObjectName>
	<Html>	
		<input type="text" size="1" id="DefaultCurrency481"></input>
		<input type="text" id="SinglePaymentAmnt"></input>
	</Html>			
	<Javascript>
		<XPath>/ds/EnterVariableData/HardshipPayment/singlePaymentAmnt</XPath>
		<componentName>##label##</componentName>
		<isMandatory>return false;</isMandatory>
		<HintText>Enter the amount of single payment - if applicable</HintText>	
		
		<validateOn>SinglePaymentAmnt.dataBinding</validateOn>		
		<validate>
			var val = Services.getValue(SinglePaymentAmnt.dataBinding);
			var err  = WPU.validateCurrency(val);
			if( null == err )
			{	Services.setValue(SinglePaymentAmnt.dataBinding, WPU.formatToTwoDP(val));
			}
			return err;
		</validate>
		<miscCode>
			function DefaultCurrency481() {}
			DefaultCurrency481.dataBinding = "/ds/EnterVariableData/curr1";
			DefaultCurrency481.tabIndex = -1;
			DefaultCurrency481.maxLength = 1;
			DefaultCurrency481.isReadOnly = function(){return true;}
			DefaultCurrency481.isTemporary = function(){return true;}
			DefaultCurrency481.transformToDisplay = function(value){
				return WPS.__CaseManUtils().transformCurrencySymbolToDisplay(value,null,null); }
			DefaultCurrency481.transformToModel = function(value){
				return WPS.__CaseManUtils().transformCurrencySymbolToModel(value,null,null); }
		</miscCode>
	</Javascript>
</Question>