<?xml version="1.0" encoding="UTF-8"?>
<Question xmlns:html="http://www.w3.org/TR/REC-html40" xmlns:xsi="http://www.w3.org/2001/XMLSchema-instance" xsi:schemaLocation="http://eds.com/questionxhtml ..\Question.xsd">
	<Id>9111</Id>
	<Label>Enter the solicitor's costs</Label>
	<ObjectName>SolicitorCost</ObjectName>
	<Html>	
		<input id="DefaultCurrency9111" type="text" size="1"></input> 
		<input id="SolicitorCost" type="text" size="9"></input>	
	</Html>
	<Javascript>
        <XPath>/ds/EnterVariableData/SolicitorCost</XPath>
		<HintText>Enter the Solicitor's Cost</HintText>
		<isMandatory>return true;</isMandatory>
        <mandatoryOn>SolicitorCost.dataBinding</mandatoryOn> 
		<validate>
			//Validation: only numeric characters allowed and two decimal places.
			//Error message: Currency amounts must be in the format of 0.00
			//Currency field. Max value. 999999.99	
            var value = Services.getValue(SolicitorCost.dataBinding);      
            var maxVal = 999999.99;         
            var err = null;
                  
            if( '0.00 ' != value )
            {   err = validateCurrencyValue(value, maxVal);
            	if( null == err)
                { 
                	var returnVal = WPU.formatToTwoDP(value);
                    Services.setValue(SolicitorCost.dataBinding, returnVal);
                } 
            }	
            return err;         		
		</validate>	
        <transformToModel>        
			if( null == value || "" == value )
			{  return "0.00 ";
			}
			else
			{ return value;
			}
		</transformToModel>
		<transformToDisplay>            
		     if( '0.00 ' == value) return "0.00";
		     return value;           
		</transformToDisplay>
        <isEnabled>return true;</isEnabled> 
        <miscCode>
			function DefaultCurrency9111() {}
			DefaultCurrency9111.dataBinding = "/ds/EnterVariableData/curr1";
			DefaultCurrency9111.tabIndex = -1;
			DefaultCurrency9111.maxLength = 1;
			DefaultCurrency9111.isReadOnly = function(){return true;}
			DefaultCurrency9111.isTemporary = function(){return true;}
			DefaultCurrency9111.transformToDisplay = function(value){
				return WPS.__CaseManUtils().transformCurrencySymbolToDisplay(value,null,null); }
			DefaultCurrency9111.transformToModel = function(value){
				return WPS.__CaseManUtils().transformCurrencySymbolToModel(value,null,null); }
		</miscCode>
	</Javascript>
</Question>