<?xml version="1.0" encoding="ISO-8859-1"?>

<categories>

<!-- AppController.js -->
  <category>
    <name>AppController</name>
    <level>ERROR</level>
  </category>

<!-- RecordsProtocol.js -->
  <category>
    <name>RecordsProtocol</name>
    <level>ERROR</level>
  </category>
  
<!-- Config.js -->  
  <category>
    <name>FormConfigCallbackObject</name>
    <level>ERROR</level>
  </category>
  <category>  
    <name>FormConfig</name>
    <level>ERROR</level>
  </category>  
  <category>
    <name>DataService</name>
    <level>ERROR</level>
  </category> 

<!-- ConfigManager.js -->  
  <category>
    <name>ConfigManager</name>
    <level>ERROR</level>
  </category>

<!-- FormController-Services.js -->  
  <category>
    <name>ExceptionFactory</name>
    <level>ERROR</level>
  </category>
  
<!-- FormController.js -->  
  <category>
    <name>FormController</name>
    <level>ERROR</level>
  </category>

<!-- GUIAdaptor.js -->  
  <category>
    <name>GUIAdaptor</name>
    <level>ERROR</level>
  </category>

<!-- GUIAdaptorFactory.js -->  
  <category>
    <name>GUIAdaptorFactory</name>
    <level>ERROR</level>
  </category>

<!-- GUIAdaptorRegistration.js -->  
  <category>
    <name>GUIAdaptorRegistration</name>
    <level>ERROR</level>
  </category>

<!-- SOAP.js -->  
  <category>
    <name>SOAPServiceProxy</name>
    <level>ERROR</level>
  </category>

<!-- TabbingManager.js -->  
  <category>
    <name>TabbingManager</name>
    <level>ERROR</level>
  </category>

<!-- Utils.js -->  
<!-- USES DEFAULT CATEGORY -->

<!-- ValidationHelper.js -->  
  <category>
    <name>ValidationHelper</name>
    <level>ERROR</level>
  </category>

<!-- XML.js -->  
<!-- USES DEFAULT CATEGORY -->

<!-- key.js -->  
  <category>
    <name>ElementKeyBindings</name>
    <level>ERROR</level>
  </category>

<!-- PopupHelp.js -->  
  <category>
    <name>PopupHelp</name>
    <level>ERROR</level>
  </category>

<!-- SUPSEvent.js -->  
  <category>
    <name>SUPSEvent</name>
    <level>ERROR</level>
  </category>

<!-- DataModel.js and DataModelMatching.js-->  
  <category>
    <name>DataModel</name>
    <level>ERROR</level>
  </category>

<!-- DataBindingProtocol.js -->  
  <category>
    <name>DataBindingProtocol</name>
    <level>ERROR</level>
  </category>

<!-- FocusProtocol.js -->  
  <category>
    <name>FocusProtocol</name>
    <level>ERROR</level>
  </category>

<!-- IteratorProtocol.js -->  
  <category>
    <name>IteratorProtocol</name>
    <level>ERROR</level>
  </category>

<!-- ListSrcDataProtocol.js -->  
  <category>
    <name>XPathUtils</name>
    <level>ERROR</level>
  </category>
  <category>
    <name>ListSrcDataProtocol</name>
    <level>ERROR</level>
  </category>

<!-- MandatoryProtocol.js -->  
  <category>
    <name>MandatoryProtocol</name>
    <level>ERROR</level>
  </category>

<!-- StateChangeEventProtocol.js -->  
  <category>
    <name>StateChangeEventProtocol</name>
    <level>ERROR</level>
  </category>
  <category>
    <name>SubmissibleState</name>
    <level>ERROR</level>
  </category>

<!-- EventQueue.js -->  
  <category>
    <name>EventQueue</name>
    <level>ERROR</level>
  </category>

<!-- AutocompletionGUIAdaptor.js -->  
  <category>
    <name>AutocompletionGUIAdaptor</name>
    <level>ERROR</level>
  </category>
  
<!-- CheckboxInputElementGUIAdaptor.js -->  
  <category>
    <name>CheckboxInputElementGUIAdaptor</name>
    <level>ERROR</level>
  </category>
  
<!-- GridGUIAdaptor.js -->  
  <category>
    <name>GridGUIAdaptor</name>
    <level>ERROR</level>
  </category>

<!-- LogicGUIAdaptor.js -->  
  <category>
    <name>LogicGUIAdaptor</name>
    <level>ERROR</level>
  </category>

<!-- LOVPopupGUIAdaptor.js -->  
  <category>
    <name>LOVPopupGUIAdaptor</name>
    <level>ERROR</level>
  </category>

<!-- PagedAreaGUIAdaptor.js -->  
  <category>
    <name>PagedAreaGUIAdaptor</name>
    <level>ERROR</level>
  </category>

<!-- PageAreaGUIAdaptor.js -->  
  <category>
    <name>PageGUIAdaptor</name>
    <level>ERROR</level>
  </category>

<!-- CheckboxInputElementGUIAdaptor.js -->  
  <category>
    <name>CheckboxInputElementGUIAdaptor</name>
    <level>ERROR</level>
  </category>

<!-- PopupGUIAdaptor.js -->  
  <category>
    <name>PopupGUIAdaptor</name>
    <level>ERROR</level>
  </category>

<!-- SelectElementAdaptor.js -->  
  <category>
    <name>SelectElementGUIAdaptor</name>
    <level>ERROR</level>
  </category>

<!-- TabSelectorGUIAdaptor.js -->  
  <category>
    <name>TabSelectorGUIAdaptor</name>
    <level>ERROR</level>
  </category>
  
<!-- TextAreaElementGUIAdaptor.js -->  
  <category>
    <name>TextAreaElementGUIAdaptor</name>
    <level>ERROR</level>
  </category>

<!-- TextInputElementGUIAdaptor.js -->  
  <category>
    <name>TextInputElementGUIAdaptor</name>
    <level>ERROR</level>
  </category>

<!-- AutoCompletionRenderer.js -->  
  <category>
    <name>AutoCompletionRenderer</name>
    <level>ERROR</level>
  </category>

<!-- DatePickerGUIAdaptor.js -->  
  <category>
    <name>DatePickerGUIAdaptor</name>
    <level>ERROR</level>
  </category>

<!-- DatePickerRenderer.js -->  
  <category>
    <name>DatePickerRenderer</name>
    <level>ERROR</level>
  </category>

<!-- FWDateUtil.js -->  
  <category>
    <name>FWDateUtil</name>
    <level>ERROR</level>
  </category>

<!-- DropDownFieldRenderer.js -->  
  <category>
    <name>DropDownFieldRenderer</name>
    <level>ERROR</level>
  </category>

<!-- LoginGUIAdaptor.js -->  
  <category>
    <name>LoginGUIAdaptor</name>
    <level>ERROR</level>
  </category>

<!-- LoginRenderer.js -->  
  <category>
    <name>LoginRenderer</name>
    <level>ERROR</level>
  </category>

<!-- Scrollbar.js -->  
  <category>
    <name>Scrollbar</name>
    <level>ERROR</level>
  </category>

<!-- StyleManager.js -->  
  <category>
    <name>StyleManager</name>
    <level>ERROR</level>
  </category>
  
<!-- SubmitFormBusinessLifeCycle.js -->
  <category>
    <name>SubmitFormBusinessLifeCycle</name>
    <level>ERROR</level>
  </category>
  
<!-- MenuBarGUIAdaptor.js -->
  <category>
    <name>MenuBarGUIAdaptor</name>
    <level>ERROR</level>
  </category>
  
<!-- MenuBarRenderer.js -->
  <category>
    <name>MenuBarRenderer</name>
    <level>ERROR</level>
  </category>
  
<!-- MenuGUIAdaptor -->
  <category>
    <name>MenuGUIAdaptor</name>
    <level>ERROR</level>
  </category>
  
<!-- MenuRenderer -->
  <category>
    <name>MenuRenderer</name>
    <level>ERROR</level>
  </category>
  
<!-- MenuPanelRenderer.js -->
  <category>
    <name>MenuPanelRenderer</name>
    <level>ERROR</level>
  </category>
  
<!-- MenuModel -->
  <category>
    <name>MenuModel</name>
    <level>ERROR</level>
  </category>
  
<!-- SubMenuComponent.js -->
  <category>
    <name>SubMenuComponent</name>
    <level>ERROR</level>
  </category>
  
<!-- AbstractPopupGUIAdaptor.js -->
  <category>
    <name>AbstractPopupGUIAdaptor</name>
    <level>ERROR</level>
  </category>
  
<!-- PopupSubformGUIAdaptor.js -->
  <category>
      <name>PopupSubformGUIAdaptor</name>
      <level>ERROR</level>
  </category>

<!-- HTMLView.js -->
  <category>
    <name>HTMLView</name>
    <level>ERROR</level>
  </category>
  
<!-- fwFileDataLoader.js -->
  <category>
    <name>fwFileDataLoader</name>
    <level>ERROR</level>
  </category>
  
<!-- fwServerCallDataService -->
  <category>
    <name>fwServerCallDataService</name>
    <level>ERROR</level>
  </category>

</categories>
